{"cameraMode":{"drawMode":0,"name":"Shaded","section":"Shading Mode"},"sceneLighting":true,"audioPlay":false,"sceneViewState":{"showFog":true,"showMaterialUpdate":false,"showSkybox":true,"showFlares":true,"showImageEffects":true,"showParticleSystems":true},"in2DMode":false,"pivot":{"x":-0.5228001475334168,"y":0.8725388646125794,"z":-1.503997802734375},"rotation":{"x":-0.2439413219690323,"y":0.36989372968673708,"z":-0.10129955410957337,"w":-0.8907383680343628},"size":1.3528012037277222,"orthographic":false}